HuggParser/HuggingFaceMetadataParser.py
HuggParser/HuggingFaceParser.py
HuggParser/__init__.py
HuggParser/default_parser.config
HuggParser/utils_hugg.py
HuggParser/mappings/mapping.yaml
huggingface2rdf-0.1.2.dist-info/licenses/LICENSE
huggingface2rdf-0.1.2.dist-info/METADATA
huggingface2rdf-0.1.2.dist-info/WHEEL
huggingface2rdf-0.1.2.dist-info/entry_points.txt
huggingface2rdf-0.1.2.dist-info/top_level.txt
huggingface2rdf-0.1.2.dist-info/RECORD
