Metadata-Version: 2.4
Name: HuggingFace2RDF
Version: 0.1.2
Summary: HuggingFace Parser converting onnx repos to rdf
Author-email: Jorge M <jorge.martin.izquierdo@upm.es>
License: Apache-2.0
Project-URL: Homepage, https://github.com/JorgeMIng/HuggParser
Requires-Python: >=3.13
License-File: LICENSE
Requires-Dist: onnx-2-rdf
Requires-Dist: onnx==1.18.0
Requires-Dist: onnxruntime==1.22.0
Requires-Dist: ruamel.yaml==0.18.10
Requires-Dist: pathvalidate==3.2.3
Requires-Dist: huggingface-hub==0.32.3
Requires-Dist: inquirerpy==0.3.4
Requires-Dist: hf-xet==1.1.2
Requires-Dist: transformers==4.52.4
Requires-Dist: tokenizers==0.21.1
Requires-Dist: tqdm==4.67.1
Requires-Dist: pandas==2.2.3
Requires-Dist: psutil==7.0.0
Requires-Dist: ipywidgets==8.1.7
Requires-Dist: ipython==9.0.2
Dynamic: license-file
